remotecap.py
remotecap-2.2.0.dist-info/LICENSE.txt
remotecap-2.2.0.dist-info/METADATA
remotecap-2.2.0.dist-info/RECORD
remotecap-2.2.0.dist-info/WHEEL
remotecap-2.2.0.dist-info/entry_points.txt
remotecap-2.2.0.dist-info/top_level.txt
