Metadata-Version: 2.1
Name: remotecap
Version: 2.2.0
Summary: Small utility to perform tcpdump on remote machines.
Home-page: https://github.com/evanfoster/remotecap
Author: Evan Foster
Author-email: evan@fos.tech
License: UNKNOWN
Project-URL: Bug Reports, https://github.com/evanfoster/remotecap
Project-URL: Source, https://github.com/evanfoster/remotecap
Keywords: tcpdump wireshark packet capture
Platform: UNKNOWN
Classifier: Development Status :: 5 - Production/Stable
Classifier: Intended Audience :: System Administrators
Classifier: Intended Audience :: Developers
Classifier: Intended Audience :: Information Technology
Classifier: Topic :: System :: Networking :: Monitoring
Classifier: License :: OSI Approved :: GNU General Public License v3 (GPLv3)
Classifier: Programming Language :: Python :: 3.6
Requires-Python: >=3.6
Provides-Extra: recommends
Requires-Dist: py-term
Requires-Dist: asyncssh
Requires-Dist: aiofiles
Provides-Extra: recommends
Requires-Dist: libnacl; extra == 'recommends'
Requires-Dist: bcrypt; extra == 'recommends'
Requires-Dist: gssapi; extra == 'recommends'
Requires-Dist: pyOpenSSL; extra == 'recommends'
